Metadata-Version: 2.1
Name: pagecache-tools
Version: 1.0.0
Summary: Set of tools to monitor memory activity.
Author: Sergio Troiano
Author-email: sergio_troiano@hotmail.com
Requires-Dist: python-daemon==3.0.1
Requires-Dist: datadog==0.46.0
Requires-Dist: pid==3.0.4
